{
  "queue_id": "sendops-2026-03-05",
  "queue_date": "2026-03-05",
  "execution_date": "2026-03-05",
  "day_of_week": "Thursday",
  "day_quality": "OPTIMAL - Thursday is #2 best day (44% open rate 9-11am)",
  "timezone_reference": "America/Los_Angeles",
  "generated_at": "2026-03-05T07:11:00-08:00",
  "status": "ready_for_execution",
  
  "daily_caps": {
    "first_touch_email": 30,
    "first_touch_sms": 20,
    "followup_cap": 60,
    "notes": "SMS capped due to Twilio trial limits (verified numbers only)"
  },

  "send_windows": [
    {
      "window_id": "AM1",
      "label": "Morning Prime",
      "time_range_local": "09:00-10:00",
      "priority": 1,
      "channel_preference": "email",
      "lead_count": 15,
      "notes": "Highest open rate window - prioritize P1 high-value leads"
    },
    {
      "window_id": "AM2", 
      "label": "Morning Secondary",
      "time_range_local": "10:00-11:00",
      "priority": 2,
      "channel_preference": "email",
      "lead_count": 15,
      "notes": "Second-highest open rate - P1 and P2 leads"
    },
    {
      "window_id": "PM1",
      "label": "Afternoon Prime",
      "time_range_local": "13:00-14:00",
      "priority": 3,
      "channel_preference": "sms",
      "lead_count": 10,
      "notes": "SMS-first for phone-only leads - landscaping/handyman owners check phones after lunch"
    },
    {
      "window_id": "PM2",
      "label": "Late Afternoon",
      "time_range_local": "15:00-16:00",
      "priority": 4,
      "channel_preference": "sms",
      "lead_count": 10,
      "notes": "Catch-up window for phone-only leads in Mountain/Central timezones"
    }
  ],

  "approval_gates": {
    "gate1_data_qa": {
      "status": "complete",
      "check": "phone/email valid + service/geo fit + no outreach duplicate <7d"
    },
    "gate2_message_qa": {
      "status": "pending",
      "check": "Run qa_email_lint.py on each message template before send"
    },
    "gate3_throughput_qa": {
      "status": "complete",
      "check": "Windows normalized per lead timezone, caps respected"
    },
    "gate4_manual_unlock": {
      "status": "pending",
      "check": "Human go/no-go before each window (Craig or auto-unlock per STANDING_ORDERS)"
    }
  },

  "followup_policy": {
    "fu1": "+24h",
    "fu1_channel": "swap (email→sms, sms→call)",
    "fu2": "+72h",
    "fu2_channel": "call+vm or nudge",
    "fu3": "+7d",
    "fu3_channel": "breakup email with CTA to demo site"
  },

  "channel_routing": {
    "email_capable": "Use Resend API (john@northstarsynergy.com)",
    "sms_capable": "Use Twilio (+14256002267) - trial mode, verified numbers",
    "call_capable": "Manual call list for fu2, or VM drop",
    "fallback": "If email bounces, swap to SMS; if SMS fails, flag for manual"
  },

  "response_tracking_fields": {
    "sent_at": "ISO timestamp when message dispatched",
    "message_id": "SMTP/API message ID for proof",
    "channel_used": "email|sms|call",
    "delivery_status": "sent|delivered|bounced|failed",
    "opened_at": "ISO timestamp if opened (email only)",
    "clicked_at": "ISO timestamp if link clicked",
    "replied_at": "ISO timestamp if reply received",
    "reply_sentiment": "positive|neutral|negative|unsubscribe",
    "followup_1_sent": "ISO timestamp",
    "followup_2_sent": "ISO timestamp", 
    "followup_3_sent": "ISO timestamp",
    "outcome": "no_response|interested|meeting_booked|declined|unsubscribe"
  },

  "batches": [
    {
      "batch_id": "P1-HIGH-VALUE",
      "priority": 1,
      "label": "High-Value First-Touch",
      "estimated_value_range": "$1000-1500",
      "services": ["Roofing", "General Contractor"],
      "channel": "email_then_sms",
      "window": "AM1",
      "lead_count": 8,
      "leads": [
        {
          "lead_id": "nosite-037",
          "client": "Regal Roofing & Contracting",
          "location": "Seattle, WA",
          "service": "Roofing/Contractor",
          "estimated_value": 1500,
          "phone": "+12067842689",
          "email": null,
          "channel": "sms",
          "timezone": "America/Los_Angeles",
          "send_window_local": "09:15",
          "contact_name": null,
          "personalization_hook": "7 photos on Yelp - active visual marketing"
        },
        {
          "lead_id": "nosite-068",
          "client": "Quality Construction & Roofing",
          "location": "Houston, TX",
          "service": "General Contractor/Roofing",
          "estimated_value": 1500,
          "phone": "+18322826486",
          "email": null,
          "channel": "sms",
          "timezone": "America/Chicago",
          "send_window_local": "10:15",
          "contact_name": null,
          "personalization_hook": "Houston construction market"
        },
        {
          "lead_id": "gpass-pnw-208",
          "client": "Lobo Roofing LLC",
          "location": "Tacoma, WA",
          "service": "Roofing",
          "estimated_value": 1200,
          "phone": "+12536513106",
          "email": "info@tacomaroofs.com",
          "channel": "email",
          "timezone": "America/Los_Angeles",
          "send_window_local": "09:20",
          "contact_name": null,
          "personalization_hook": "24-hour service positioning - urgent lead capture"
        },
        {
          "lead_id": "gpass-pnw-214",
          "client": "Forever Roofing",
          "location": "Seattle, WA",
          "service": "Roofing",
          "estimated_value": 1200,
          "phone": "+12062613683",
          "email": "info@foreverroofing.net",
          "channel": "email",
          "timezone": "America/Los_Angeles",
          "send_window_local": "09:30",
          "contact_name": null,
          "personalization_hook": "Seattle metro roofing market"
        },
        {
          "lead_id": "gpass-pnw-219",
          "client": "A Better Roofing Company",
          "location": "Seattle, WA",
          "service": "Residential Roofing",
          "estimated_value": 1200,
          "phone": "+12069351575",
          "email": "abr@abetterroofing.com",
          "channel": "email",
          "timezone": "America/Los_Angeles",
          "send_window_local": "09:40",
          "contact_name": null,
          "personalization_hook": "Residential focus - homeowner market"
        },
        {
          "lead_id": "gpass-pnw-220",
          "client": "Quality Pacific Roofing",
          "location": "Seattle, WA 98122",
          "service": "Residential Roofing",
          "estimated_value": 1200,
          "phone": "+12062640955",
          "email": "Info@QualityPacificRoofing.com",
          "channel": "email",
          "timezone": "America/Los_Angeles",
          "send_window_local": "09:45",
          "contact_name": null,
          "personalization_hook": "Strong local site - verified contact page",
          "priority_score": 88
        },
        {
          "lead_id": "gpass-pnw-210",
          "client": "Elite Metal Roofing LLC",
          "location": "Vancouver, WA",
          "service": "Roofing",
          "estimated_value": 1200,
          "phone": "+13604879090",
          "email": "Robert@elitemetalroofingllc.com",
          "channel": "email",
          "timezone": "America/Los_Angeles",
          "send_window_local": "09:50",
          "contact_name": "Robert",
          "personalization_hook": "Metal roofing specialist - premium positioning"
        },
        {
          "lead_id": "nosite-109",
          "client": "San Diego Heating and Cooling",
          "location": "San Diego, CA",
          "service": "HVAC",
          "estimated_value": 900,
          "phone": "+16194432665",
          "email": null,
          "channel": "sms",
          "timezone": "America/Los_Angeles",
          "send_window_local": "09:55",
          "contact_name": null,
          "personalization_hook": "San Diego HVAC market"
        }
      ]
    },
    {
      "batch_id": "P2-MEDIUM-VALUE",
      "priority": 2,
      "label": "Medium-Value First-Touch",
      "estimated_value_range": "$750-950",
      "services": ["Landscaping", "Fencing", "Handyman"],
      "channel": "email_then_sms",
      "window": "AM2",
      "lead_count": 12,
      "leads": [
        {
          "lead_id": "gpass-pnw-224",
          "client": "Greenscape Landscaping of Spokane",
          "location": "Spokane, WA",
          "service": "Landscaping",
          "estimated_value": 850,
          "phone": "+15094610525",
          "email": "contact@spokanegreenscape.com",
          "channel": "email",
          "timezone": "America/Los_Angeles",
          "send_window_local": "10:00",
          "contact_name": null,
          "personalization_hook": "Strong local site, serves North Idaho too",
          "priority_score": 87
        },
        {
          "lead_id": "gpass-pnw-213",
          "client": "Handyman Rescue Team",
          "location": "Seattle, WA",
          "service": "Handyman/Remodeling",
          "estimated_value": 900,
          "phone": "+12067363060",
          "email": "sos@handymanrescue.team",
          "channel": "email",
          "timezone": "America/Los_Angeles",
          "send_window_local": "10:10",
          "contact_name": null,
          "personalization_hook": "Clever branding (SOS email) - marketing savvy",
          "priority_score": 86
        },
        {
          "lead_id": "gpass-pnw-207",
          "client": "Green Leaf Landscaping of Washington",
          "location": "Battle Ground, WA",
          "service": "Landscaping",
          "estimated_value": 800,
          "phone": "+13609474166",
          "email": "info@greenleaflandscapingwa.com",
          "channel": "email",
          "timezone": "America/Los_Angeles",
          "send_window_local": "10:20",
          "contact_name": null,
          "personalization_hook": "Weak brochure site - clear upgrade opportunity"
        },
        {
          "lead_id": "gpass-pnw-209",
          "client": "Fitzpatrick Fence & Rail",
          "location": "Portland, OR",
          "service": "Fencing",
          "estimated_value": 900,
          "phone": "+15034537737",
          "email": "fitzpatrickfence@frontier.com",
          "channel": "email",
          "timezone": "America/Los_Angeles",
          "send_window_local": "10:30",
          "contact_name": null,
          "personalization_hook": "Portland fencing market"
        },
        {
          "lead_id": "gpass-pnw-223",
          "client": "A1 Handyman",
          "location": "Boise, ID",
          "service": "Handyman",
          "estimated_value": 700,
          "phone": "+12089956457",
          "email": "mrhandymanid@gmail.com",
          "channel": "email",
          "timezone": "America/Boise",
          "send_window_local": "10:40",
          "contact_name": null,
          "personalization_hook": "Boise handyman market"
        },
        {
          "lead_id": "gpass-pnw-211",
          "client": "Boise Landscaping and Lawn Care",
          "location": "Boise, ID",
          "service": "Landscaping",
          "estimated_value": 750,
          "phone": "+12086711044",
          "email": "info@landscapinginboise.com",
          "channel": "email",
          "timezone": "America/Boise",
          "send_window_local": "10:45",
          "contact_name": null,
          "personalization_hook": "Adjacent metro expansion"
        },
        {
          "lead_id": "nosite-001",
          "client": "Perez Landscaping",
          "location": "Seattle, WA 98188",
          "service": "Landscaping",
          "estimated_value": 800,
          "phone": "+12066029766",
          "email": null,
          "channel": "sms",
          "timezone": "America/Los_Angeles",
          "send_window_local": "10:50",
          "contact_name": null,
          "personalization_hook": "Latino-owned in SeaTac/Tukwila - local market"
        },
        {
          "lead_id": "nosite-002",
          "client": "Ligaya Landscaping",
          "location": "Seattle, WA 98101",
          "service": "Landscaping",
          "estimated_value": 800,
          "phone": "+12063517402",
          "email": null,
          "channel": "sms",
          "timezone": "America/Los_Angeles",
          "send_window_local": "10:52",
          "contact_name": null,
          "personalization_hook": "Downtown Seattle - high-density service area"
        },
        {
          "lead_id": "nosite-003",
          "client": "Greenscapes Landscaping",
          "location": "Seattle, WA 98146",
          "service": "Landscaping",
          "estimated_value": 800,
          "phone": "+12068028186",
          "email": null,
          "channel": "sms",
          "timezone": "America/Los_Angeles",
          "send_window_local": "10:54",
          "contact_name": null,
          "personalization_hook": "West Seattle location"
        },
        {
          "lead_id": "nosite-004",
          "client": "Northwest Landscape and Patio Bellevue",
          "location": "Bellevue, WA",
          "service": "Landscaping",
          "estimated_value": 800,
          "phone": "+14253904959",
          "email": null,
          "channel": "sms",
          "timezone": "America/Los_Angeles",
          "send_window_local": "10:56",
          "contact_name": null,
          "personalization_hook": "Bellevue affluent market"
        },
        {
          "lead_id": "nosite-005",
          "client": "Envision Landscaping",
          "location": "Bellevue, WA",
          "service": "Landscaping",
          "estimated_value": 800,
          "phone": "+12066798525",
          "email": null,
          "channel": "sms",
          "timezone": "America/Los_Angeles",
          "send_window_local": "10:58",
          "contact_name": null,
          "personalization_hook": "Bellevue area"
        },
        {
          "lead_id": "nosite-033",
          "client": "A A Landscaping",
          "location": "Bothell, WA",
          "service": "Landscaping",
          "estimated_value": 800,
          "phone": "+12062518199",
          "email": null,
          "channel": "sms",
          "timezone": "America/Los_Angeles",
          "send_window_local": "11:00",
          "contact_name": null,
          "personalization_hook": "Bothell - same market as Antonio/Lustre"
        }
      ]
    },
    {
      "batch_id": "P3-SMS-AFTERNOON",
      "priority": 3,
      "label": "SMS Afternoon Batch",
      "estimated_value_range": "$500-800",
      "services": ["Handyman", "Cleaning", "Pool Service"],
      "channel": "sms",
      "window": "PM1",
      "lead_count": 10,
      "leads": [
        {
          "lead_id": "nosite-006",
          "client": "Home-Crafters-Handyman",
          "location": "Kirkland, WA",
          "service": "Handyman",
          "estimated_value": 600,
          "phone": "+12062356574",
          "email": null,
          "channel": "sms",
          "timezone": "America/Los_Angeles",
          "send_window_local": "13:00",
          "contact_name": null,
          "personalization_hook": "Kirkland local handyman"
        },
        {
          "lead_id": "nosite-007",
          "client": "Half-Price Handyman",
          "location": "Kirkland, WA",
          "service": "Handyman",
          "estimated_value": 600,
          "phone": "+14252698545",
          "email": null,
          "channel": "sms",
          "timezone": "America/Los_Angeles",
          "send_window_local": "13:05",
          "contact_name": null,
          "personalization_hook": "Value positioning - budget-conscious clients"
        },
        {
          "lead_id": "nosite-008",
          "client": "R & S Cleaning Services",
          "location": "Redmond, WA",
          "service": "House Cleaning",
          "estimated_value": 500,
          "phone": "+14257803018",
          "email": null,
          "channel": "sms",
          "timezone": "America/Los_Angeles",
          "send_window_local": "13:10",
          "contact_name": null,
          "personalization_hook": "Redmond residential cleaning"
        },
        {
          "lead_id": "nosite-023",
          "client": "Handy-Den",
          "location": "Tacoma, WA",
          "service": "Handyman",
          "estimated_value": 600,
          "phone": "+12532302928",
          "email": null,
          "channel": "sms",
          "timezone": "America/Los_Angeles",
          "send_window_local": "13:15",
          "contact_name": "Den",
          "personalization_hook": "Has contact name - personalize message"
        },
        {
          "lead_id": "nosite-055",
          "client": "Tony Handyman Survives",
          "location": "Phoenix, AZ",
          "service": "Handyman",
          "estimated_value": 600,
          "phone": "+14807407144",
          "email": null,
          "channel": "sms",
          "timezone": "America/Phoenix",
          "send_window_local": "14:00",
          "contact_name": "Tony",
          "personalization_hook": "Has contact name Tony"
        },
        {
          "lead_id": "nosite-056",
          "client": "Rick The Handyman",
          "location": "Phoenix, AZ",
          "service": "Handyman",
          "estimated_value": 600,
          "phone": "+16022004521",
          "email": null,
          "channel": "sms",
          "timezone": "America/Phoenix",
          "send_window_local": "14:05",
          "contact_name": "Rick",
          "personalization_hook": "Has contact name Rick"
        },
        {
          "lead_id": "nosite-057",
          "client": "Manny Handyman Svcs",
          "location": "Phoenix, AZ",
          "service": "Handyman",
          "estimated_value": 600,
          "phone": "+14804508097",
          "email": null,
          "channel": "sms",
          "timezone": "America/Phoenix",
          "send_window_local": "14:10",
          "contact_name": "Manny",
          "personalization_hook": "Has contact name Manny"
        },
        {
          "lead_id": "nosite-061",
          "client": "JV Pool Services",
          "location": "Dallas, TX",
          "service": "Pool & Hot Tub Service",
          "estimated_value": 700,
          "phone": "+12149294278",
          "email": null,
          "channel": "sms",
          "timezone": "America/Chicago",
          "send_window_local": "14:00",
          "contact_name": null,
          "personalization_hook": "Dallas pool service market"
        },
        {
          "lead_id": "nosite-049",
          "client": "Valle Landscaping",
          "location": "Phoenix, AZ",
          "service": "Landscaping",
          "estimated_value": 800,
          "phone": "+14808069550",
          "email": null,
          "channel": "sms",
          "timezone": "America/Phoenix",
          "send_window_local": "13:20",
          "contact_name": null,
          "personalization_hook": "Phoenix landscaping"
        },
        {
          "lead_id": "nosite-050",
          "client": "Valley Landscaping",
          "location": "Phoenix, AZ",
          "service": "Landscaping",
          "estimated_value": 800,
          "phone": "+16234864922",
          "email": null,
          "channel": "sms",
          "timezone": "America/Phoenix",
          "send_window_local": "13:25",
          "contact_name": null,
          "personalization_hook": "Phoenix metro landscaping"
        }
      ]
    },
    {
      "batch_id": "P4-LATE-AFTERNOON",
      "priority": 4,
      "label": "Late Afternoon Catch-Up",
      "estimated_value_range": "$700-900",
      "services": ["Fencing", "Roofing", "Auto Repair"],
      "channel": "sms",
      "window": "PM2",
      "lead_count": 10,
      "leads": [
        {
          "lead_id": "nosite-052",
          "client": "CC Landscaping",
          "location": "Phoenix, AZ",
          "service": "Landscaping",
          "estimated_value": 800,
          "phone": "+16233249775",
          "email": null,
          "channel": "sms",
          "timezone": "America/Phoenix",
          "send_window_local": "15:00",
          "contact_name": null,
          "personalization_hook": "Phoenix landscaping service"
        },
        {
          "lead_id": "nosite-053",
          "client": "RB Landscaping Service",
          "location": "Phoenix, AZ",
          "service": "Landscaping",
          "estimated_value": 800,
          "phone": "+14805408509",
          "email": null,
          "channel": "sms",
          "timezone": "America/Phoenix",
          "send_window_local": "15:05",
          "contact_name": null,
          "personalization_hook": "Landscape design services"
        },
        {
          "lead_id": "nosite-101",
          "client": "Cedar Fencing Plus",
          "location": "Portland, OR",
          "service": "Fencing",
          "estimated_value": 900,
          "phone": "+15032446216",
          "email": null,
          "channel": "sms",
          "timezone": "America/Los_Angeles",
          "send_window_local": "15:10",
          "contact_name": null,
          "personalization_hook": "Portland fencing market"
        },
        {
          "lead_id": "nosite-102",
          "client": "Austin's Custom Fencing",
          "location": "Portland, OR",
          "service": "Fencing",
          "estimated_value": 900,
          "phone": "+15037626010",
          "email": null,
          "channel": "sms",
          "timezone": "America/Los_Angeles",
          "send_window_local": "15:15",
          "contact_name": null,
          "personalization_hook": "Custom fencing - premium positioning"
        },
        {
          "lead_id": "nosite-115",
          "client": "Ace Fencing",
          "location": "Las Vegas, NV",
          "service": "Fencing",
          "estimated_value": 900,
          "phone": "+17025688330",
          "email": null,
          "channel": "sms",
          "timezone": "America/Los_Angeles",
          "send_window_local": "15:20",
          "contact_name": null,
          "personalization_hook": "Las Vegas market"
        },
        {
          "lead_id": "nosite-116",
          "client": "Bachman Lawn Care",
          "location": "Kansas City, MO",
          "service": "Lawn Care",
          "estimated_value": 700,
          "phone": "+18165508823",
          "email": null,
          "channel": "sms",
          "timezone": "America/Chicago",
          "send_window_local": "16:00",
          "contact_name": null,
          "personalization_hook": "Kansas City lawn care"
        },
        {
          "lead_id": "wave3-002",
          "client": "Nash Auto Repair",
          "location": "Milwaukee, WI",
          "service": "Auto Repair",
          "estimated_value": 800,
          "phone": "+14143930200",
          "email": null,
          "channel": "sms",
          "timezone": "America/Chicago",
          "send_window_local": "15:30",
          "contact_name": null,
          "personalization_hook": "Milwaukee auto service"
        },
        {
          "lead_id": "wave3-006",
          "client": "Garrico Plumbing",
          "location": "Raleigh, NC",
          "service": "Plumbing",
          "estimated_value": 900,
          "phone": "+19199108013",
          "email": null,
          "channel": "sms",
          "timezone": "America/New_York",
          "send_window_local": "16:00",
          "contact_name": null,
          "personalization_hook": "Raleigh plumbing market"
        },
        {
          "lead_id": "wave3-007",
          "client": "Dazco Plumbing",
          "location": "Raleigh, NC",
          "service": "Plumbing",
          "estimated_value": 900,
          "phone": "+19197878256",
          "email": null,
          "channel": "sms",
          "timezone": "America/New_York",
          "send_window_local": "16:05",
          "contact_name": null,
          "personalization_hook": "Raleigh plumbing service"
        },
        {
          "lead_id": "wave3-047",
          "client": "Electrical Solutions",
          "location": "Oklahoma City, OK",
          "service": "Electrical",
          "estimated_value": 1000,
          "phone": "+14057940200",
          "email": null,
          "channel": "sms",
          "timezone": "America/Chicago",
          "send_window_local": "15:45",
          "contact_name": null,
          "personalization_hook": "OKC electrical services"
        }
      ]
    }
  ],

  "totals": {
    "first_touch_count": 40,
    "email_sends": 15,
    "sms_sends": 25,
    "estimated_pipeline_value": 34900,
    "expected_response_rate": "7-10%",
    "expected_responses": "3-4 replies"
  },

  "execution_checklist": [
    "□ Gate2: Run qa_email_lint.py on email templates",
    "□ Gate4: Craig unlock or auto-proceed per STANDING_ORDERS Tier 2",
    "□ AM1 Window (09:00-10:00 PT): Send P1 batch emails",
    "□ AM2 Window (10:00-11:00 PT): Send P2 batch emails + SMS",
    "□ PM1 Window (13:00-14:00 PT): Send P3 SMS batch",
    "□ PM2 Window (15:00-16:00 PT): Send P4 SMS batch",
    "□ Log all message_ids to response tracker",
    "□ EOD: Update leads.jsonl with send status",
    "□ EOD: Post pipeline update in Discord #general"
  ]
}
